networklib.py
networklib-0.0.6.dist-info/DESCRIPTION.rst
networklib-0.0.6.dist-info/METADATA
networklib-0.0.6.dist-info/RECORD
networklib-0.0.6.dist-info/WHEEL
networklib-0.0.6.dist-info/metadata.json
networklib-0.0.6.dist-info/top_level.txt
