Metadata-Version: 2.0
Name: networklib
Version: 0.0.6
Summary: download and upload flv,images
Home-page: http://www.zhaomingming.cn
Author: zhaomingming
Author-email: 13271929138@163.com
License: MIT
Platform: any
